alignak_webui_graphite/__init__.py
alignak_webui_graphite/graphite_utils.py
alignak_webui_graphite/module.py
alignak_webui_graphite/util.py
alignak_webui_graphite/etc/alignak.d/alignak-module-webui-graphite.ini
alignak_webui_graphite/etc/modules/ui-graphite2.cfg
alignak_webui_graphite/etc/modules/ui-graphite-templates/check-host-alive.graph
alignak_webui_graphite/etc/modules/ui-graphite-templates/check_cpu.graph
alignak_webui_graphite/etc/modules/ui-graphite-templates/check_cpu_-4h.graph
alignak_webui_graphite/etc/modules/ui-graphite-templates/check_host_alive_ipv4.graph
alignak_webui_graphite/etc/modules/ui-graphite-templates/check_http.graph
alignak_webui_graphite/etc/modules/ui-graphite-templates/check_linux_cpu.graph
alignak_webui_graphite/etc/modules/ui-graphite-templates/check_linux_load.graph
alignak_webui_graphite/etc/modules/ui-graphite-templates/check_linux_memory.graph
alignak_webui_graphite/etc/modules/ui-graphite-templates/check_load.graph
alignak_webui_graphite/etc/modules/ui-graphite-templates/check_mem.graph
alignak_webui_graphite/etc/modules/ui-graphite-templates/check_ping.graph
alignak_webui_graphite/etc/modules/ui-graphite-templates/dashboard/check_http.graph
alignak_webui_graphite-1.1.0.data/data/share/alignak/etc/alignak.d/alignak-module-webui-graphite.ini
alignak_webui_graphite-1.1.0.data/data/share/alignak/etc/modules/ui-graphite2.cfg
alignak_webui_graphite-1.1.0.data/data/share/alignak/etc/modules/ui-graphite-templates/check-host-alive.graph
alignak_webui_graphite-1.1.0.data/data/share/alignak/etc/modules/ui-graphite-templates/check_cpu.graph
alignak_webui_graphite-1.1.0.data/data/share/alignak/etc/modules/ui-graphite-templates/check_cpu_-4h.graph
alignak_webui_graphite-1.1.0.data/data/share/alignak/etc/modules/ui-graphite-templates/check_host_alive_ipv4.graph
alignak_webui_graphite-1.1.0.data/data/share/alignak/etc/modules/ui-graphite-templates/check_http.graph
alignak_webui_graphite-1.1.0.dist-info/LICENSE
alignak_webui_graphite-1.1.0.dist-info/METADATA
alignak_webui_graphite-1.1.0.dist-info/WHEEL
alignak_webui_graphite-1.1.0.dist-info/top_level.txt
alignak_webui_graphite-1.1.0.dist-info/RECORD
